setup.py
get_merge/__init__.py
git_get_merge.egg-info/PKG-INFO
git_get_merge.egg-info/SOURCES.txt
git_get_merge.egg-info/dependency_links.txt
git_get_merge.egg-info/entry_points.txt
git_get_merge.egg-info/requires.txt
git_get_merge.egg-info/top_level.txt