Metadata-Version: 1.0
Name: git-get-merge
Version: 0.1
Summary: A git command to find the merge that introduced a given commit.
Home-page: http://github.com/jianli/git-get-merge
Author: UNKNOWN
Author-email: UNKNOWN
License: UNKNOWN
Platform: UNKNOWN
